{"name":"몰수금품 등 처리에 관한 임시특례법","ef":"20181218","old":[{"content":"<P>沒收金品等處理에關한臨時特例法</P>","no":"1"},{"content":"제1조(목적) <P>본법은 국가보안법의</P> 정한 죄를 범한 자로부터 몰수하거나 <P>또는 국고귀속명령된 금품을 타법령의 규정에</P> 불구하고 국가안전보장을 위하여 신속하고 유효적절하게 처리함을 목적으로 한다.","no":"2"},{"content":"제2조(몰수금품의 정의) <P>본법</P>에서 몰수금품이라 함은 다음 <P>각호의1</P>에 해당하는 자로부터 몰수한 무기류, 통신기재, <P>장비 기타</P> 물품과 유가증권, <P>통화등</P> 공작금품으로서 확정판결에서 몰수되거나 <P>국가보안법</P> 제15조제2항 및 <P>제22조의 규정에 의하여</P> 국고귀속명령된 것을 말한다.","no":"3"},{"content":"1.·2. (생  략)","no":"4"},{"content":"3. <P>전각호</P>에 규정된 자로부터 지령을 받아 활동을 하는 자","no":"5"},{"content":"4. (생  략)","no":"6"},{"content":"제3조(몰수금품의 처리) ①국가정보원장은 <P>몰수금품중</P> 첩보공작상 또는 공익상 필요하다고 인정되는 금품의 일부 또는 전부를 국무회의의 심의를 거쳐 대통령의 승인을 얻어 이를 직접사용 또는 처분할 수 있다.","no":"7"},{"content":"②국가정보원장은 <P>전항의 규정에 의하여 직접사용한 몰수금품중</P> 대한민국화폐에 대하여는 그와 <P>동액의</P> 금액을 국가정보원 <P>세출금중</P>에서 공제하여 이를 국고에 납부하여야 한다.","no":"8"},{"content":"제4조(시행령) <P>본법 시행에 관하여</P> 필요한 사항은 대통령령으로 정한다.","no":"9"}],"new":[{"content":"<P>몰수금품 등 처리에 관한 임시특례법</P>","no":"1"},{"content":"제1조(목적) <P>이 법은 「국가보안법」에서</P> 정한 죄를 범한 자로부터 몰수하거나 <P>국고귀속명령된 금품을 다른 법령의 규정에도</P> 불구하고 국가안전보장을 위하여 신속하고 유효적절하게 처리함을 목적으로 한다.","no":"2"},{"content":"제2조(몰수금품의 정의) <P>이 법</P>에서 몰수금품이라 함은 다음 <P>각 호의 어느 하나</P>에 해당하는 자로부터 몰수한 무기류, 통신기재, <P>장비, 그 밖의</P> 물품과 유가증권, <P>통화 등</P> 공작금품으로서 확정판결에서 몰수되거나 <P>「국가보안법」</P> 제15조제2항 및 <P>제22조에 따라</P> 국고귀속명령된 것을 말한다.","no":"3"},{"content":"1.·2. (현행과 같음)","no":"4"},{"content":"3. <P>제1호 및 제2호</P>에 규정된 자로부터 지령을 받아 활동을 하는 자","no":"5"},{"content":"4. (현행과 같음)","no":"6"},{"content":"제3조(몰수금품의 처리) ①국가정보원장은 <P>몰수금품 중</P> 첩보공작상 또는 공익상 필요하다고 인정되는 금품의 일부 또는 전부를 국무회의의 심의를 거쳐 대통령의 승인을 얻어 이를 직접사용 또는 처분할 수 있다.","no":"7"},{"content":"②국가정보원장은 <P>제1항에 따라 직접사용한 몰수금품 중</P> 대한민국화폐에 대하여는 그와 <P>같은</P> 금액을 국가정보원 <P>세출금 중</P>에서 공제하여 이를 국고에 납부하여야 한다.","no":"8"},{"content":"제4조(시행령) <P>이 법 시행에</P> 필요한 사항은 대통령령으로 정한다.","no":"9"}]}