{"name":"행정업무의 운영 및 혁신에 관한 규정 시행규칙","ef":"20230628","old":[{"content":"<P>행정 효율과 협업 촉진에 관한 규정 시행규칙</P>","no":"1"},{"content":"제1조(목적) 이 규칙은 <P>「행정 효율과 협업 촉진에 관한 규정」</P>에서 위임된 사항과 그 시행에 필요한 사항을 규정함을 목적으로 한다.","no":"2"},{"content":"제2조<P>(공문서 작성의 일반원칙)</P>   ② 문서에 금액을 표시할 때에는 <P>「행정 효율과 협업 촉진에 관한 규정」(이하</P> “영”이라 한다) 제7조제4항에 따라 아라비아 숫자로 쓰되, 숫자 다음에 괄호를 하고 다음과 같이 한글로 적어야 한다.   (예시) 금113,560원(금일십일만삼천오백육십원)","no":"3"},{"content":"<P>제23조(서식의 지질 등) ① 서식을 포함한 용지의 용도별 지질 기준은 별표 3과 같다. 다만, 부득이한 경우에는 별표 3에 따른 기준과 다른 지질의 용지를 사용할 수 있다.② 서식에는 용지의 규격과 지질을 다음의 예시와 같이 해당 서식의 우측 하단에 표시한다.  (예시) 210㎜×297㎜(백상지 80g/㎡)</P>","no":"4"}],"new":[{"content":"<P>행정업무의 운영 및 혁신에 관한 규정 시행규칙</P>","no":"1"},{"content":"제1조(목적) 이 규칙은 <P>「행정업무의 운영 및 혁신에 관한 규정」</P>에서 위임된 사항과 그 시행에 필요한 사항을 규정함을 목적으로 한다.","no":"2"},{"content":"제2조<P>(공문서 작성의 방법)</P>   ② 문서에 금액을 표시할 때에는 <P>「행정업무의 운영 및 혁신에 관한 규정」(이하</P> “영”이라 한다) 제7조제4항에 따라 아라비아 숫자로 쓰되, 숫자 다음에 괄호를 하고 다음과 같이 한글로 적어야 한다. (예시) 금113,560원(금일십일만삼천오백육십원)","no":"3"},{"content":"<P>제23조(용지의 규격 등 표시) 영 제28조제7항에 따라 서식에 용지의 규격 등을 표시하는 경우에는 다음의 예시와 같이 해당 서식의 우측 하단에 표시한다.</P>","no":"4"}]}