{"name":"국민권익위원회와 그 소속기관 직제","ef":"20250101","old":[{"content":"제15조(위원회에 두는 공무원의 정원) ① ∼ ④ (생  략)","no":"1"},{"content":"⑤ 제1항 및 별표 1에 따른 위원회의 정원 중 <P>2명(5급 2명)</P>은 감사원, 1명(5급 1명)은 교육부, 1명(6급 1명)은 과학기술정보통신부, 1명(6급 1명)은 법무부, 2명(5급 1명, 6급 1명)은 행정안전부, 2명(5급 1명, 6급 1명)은 국가보훈부, 2명(5급 1명, 6급 1명)은 문화체육관광부, 2명(5급 1명, 6급 1명)은 <P>농림축산식품부, 2명(6급 2명)</P>은 산업통상자원부, 2명(5급 1명, 6급 1명)은 보건복지부, 1명(5급 1명)은 환경부, 2명(5급 1명, 6급 1명)은 고용노동부, 7명(5급 4명, 6급 3명)은 국토교통부, 1명(6급 1명)은 <P>해양수산부, 1명(5급 1명)은 법제처</P>, 2명(6급 2명)은 국세청, 3명(경정 1명, 경감 2명)은 경찰청 소속 공무원으로 각각 충원할 수 있다.","no":"2"},{"content":"<P>제18조(한시정원) ① 공공기관의 채용비리 근절을 위한 관련 제도의 운영, 신고의 처리 및 실태조사 등의 업무를 수행하기 위하여 「행정기관의 조직과 정원에 관한 통칙」 제25조제1항에 따라 2024년 12월 31일까지 별표 4에 따른 한시정원을 국민권익위원회에 둔다.② 온라인 국민참여포털 등을 통하여 제출된 국민제안 등의 관리 체계를 효율적으로 운영하기 위하여 「행정기관의 조직과 정원에 관한 통칙」 제25조제1항에 따라 2025년 12월 31일까지 별표 4에 따른 한시정원을 국민권익위원회에 둔다.</P>","no":"3"}],"new":[{"content":"제15조(위원회에 두는 공무원의 정원) ① ∼ ④ (현행과 같음)","no":"1"},{"content":"⑤ 제1항 및 별표 1에 따른 위원회의 정원 중 <P>1명(5급 1명)</P>은 감사원, 1명(5급 1명)은 교육부, 1명(6급 1명)은 과학기술정보통신부, 1명(6급 1명)은 법무부, 2명(5급 1명, 6급 1명)은 행정안전부, 2명(5급 1명, 6급 1명)은 국가보훈부, 2명(5급 1명, 6급 1명)은 문화체육관광부, 2명(5급 1명, 6급 1명)은 <P>농림축산식품부, 1명(6급 1명)</P>은 산업통상자원부, 2명(5급 1명, 6급 1명)은 보건복지부, 1명(5급 1명)은 환경부, 2명(5급 1명, 6급 1명)은 고용노동부, 7명(5급 4명, 6급 3명)은 국토교통부, 1명(6급 1명)은 <P>해양수산부</P>, 2명(6급 2명)은 국세청, 3명(경정 1명, 경감 2명)은 경찰청 소속 공무원으로 각각 충원할 수 있다.","no":"2"},{"content":"<P>제18조(한시정원) 온라인 국민참여포털 등을 통하여 제출된 국민제안 등의 관리 체계를 효율적으로 운영하기 위하여 「행정기관의 조직과 정원에 관한 통칙」 제25조제1항에 따라 2025년 12월 31일까지 별표 4에 따른 한시정원을 국민권익위원회에 둔다.</P>","no":"3"}]}