{"name":"대학설립ㆍ운영 규정","ef":"20250225","old":[{"content":"제2조(설립인가기준 등) ① ∼ ⑤ (생  략)","no":"1"},{"content":"⑥ 제4조에 따른 교사 및 제5조에 따른 교지는 설립주체의 소유여야 한다. 다만, 다음 각 호의 어느 하나에 해당하는 경우에는 그렇지 않다.","no":"2"},{"content":"1. ∼ 5. (생  략)","no":"3"},{"content":"<P><신  설></P>","no":"4"},{"content":"⑦ ∼ ⑨ (생  략)","no":"5"}],"new":[{"content":"제2조(설립인가기준 등) ① ∼ ⑤ (현행과 같음)","no":"1"},{"content":"⑥ 제4조에 따른 교사 및 제5조에 따른 교지는 설립주체의 소유여야 한다. 다만, 다음 각 호의 어느 하나에 해당하는 경우에는 그렇지 않다.","no":"2"},{"content":"1. ∼ 5. (현행과 같음)","no":"3"},{"content":"<P>6. 국립대학과 공립대학의 통ㆍ폐합에 따라 통ㆍ폐합 후 국립대학이 통ㆍ폐합 전 공립대학의 교사 또는 교지를 사용하는 경우</P>","no":"4"},{"content":"⑦ ∼ ⑨ (현행과 같음)","no":"5"}]}