{"name":"문화체육관광부와 그 소속기관 직제 시행규칙","ef":"20250225","old":[{"content":"제8조(문화예술정책실) ① ∼ ⑧ (생  략)","no":"1"},{"content":"⑨ 전통문화과장은 다음 사항을 분장한다.","no":"2"},{"content":"1. ∼ 7. (생  략)","no":"3"},{"content":"<P>8. 삭제</P>","no":"4"},{"content":"<P><신  설></P>","no":"5"},{"content":"⑩ ∼ ⑫ (생  략)","no":"6"},{"content":"⑬ 시각예술디자인과장은 다음 사항을 분장한다.","no":"7"},{"content":"1. ∼ 8. (생  략)","no":"8"},{"content":"<P>8의2. 공예문화산업 기반조성 및 법령ㆍ제도 개선</P>","no":"9"},{"content":"9. ∼ 14. (생  략)","no":"10"},{"content":"<P>15. 한국공예디자인문화진흥원과 관련된 업무</P>","no":"11"},{"content":"16. (생  략)","no":"12"},{"content":"⑭ ∼ <18> (생  략)","no":"13"}],"new":[{"content":"제8조(문화예술정책실) ① ∼ ⑧ (현행과 같음)","no":"1"},{"content":"⑨ 전통문화과장은 다음 사항을 분장한다.","no":"2"},{"content":"1. ∼ 7. (현행과 같음)","no":"3"},{"content":"<P>8. 공예문화산업 기반조성 및 법령ㆍ제도 개선</P>","no":"4"},{"content":"<P>9. 한국공예디자인문화진흥원과 관련된 업무</P>","no":"5"},{"content":"⑩ ∼ ⑫ (현행과 같음)","no":"6"},{"content":"⑬ 시각예술디자인과장은 다음 사항을 분장한다.","no":"7"},{"content":"1. ∼ 8. (현행과 같음)","no":"8"},{"content":"<P><삭  제></P>","no":"9"},{"content":"9. ∼ 14. (현행과 같음)","no":"10"},{"content":"<P><삭  제></P>","no":"11"},{"content":"16. (현행과 같음)","no":"12"},{"content":"⑭ ∼ <18> (현행과 같음)","no":"13"}]}