{"name":"선거관리위원회 공무원 규칙","ef":"20250620","old":[{"content":"제33조의2(능력검정시험의 실시 등) ①·② (생  략)","no":"1"},{"content":"③ 제1항에 따른 능력검정시험에서 우수한 성적을 받은 사람에 대하여는 제33조제3항 <P>단서에 따른 승진심사에</P> 가점을 부여할 수 있다.","no":"2"},{"content":"④ ∼ ⑦ (생  략)","no":"3"},{"content":"제93조(응시수수료) ①·② (생  략)","no":"4"},{"content":"③ 시험실시기관의 장은 제1항에도 불구하고 응시원서 접수 당시 다음 각 호의 어느 하나에 해당하는 사람에 대해서는 사무총장이 정하는 바에 따라 응시수수료를 면제할 수 있다.","no":"5"},{"content":"1. ∼ 3. (생  략)","no":"6"},{"content":"<P>4. 법 제28조제2항제7호에 따른 지방공무원</P>","no":"7"},{"content":"5. (생  략)","no":"8"}],"new":[{"content":"제33조의2(능력검정시험의 실시 등) ①·② (현행과 같음)","no":"1"},{"content":"③ 제1항에 따른 능력검정시험에서 우수한 성적을 받은 사람에 대하여는 제33조제3항 <P>단서의 실적심사승진후보자명부에 등재된 사람에 한하여</P> 가점을 부여할 수 있다.","no":"2"},{"content":"④ ∼ ⑦ (현행과 같음)","no":"3"},{"content":"제93조(응시수수료) ①·② (현행과 같음)","no":"4"},{"content":"③ 시험실시기관의 장은 제1항에도 불구하고 응시원서 접수 당시 다음 각 호의 어느 하나에 해당하는 사람에 대해서는 사무총장이 정하는 바에 따라 응시수수료를 면제할 수 있다.","no":"5"},{"content":"1. ∼ 3. (현행과 같음)","no":"6"},{"content":"<P><삭  제></P>","no":"7"},{"content":"5. (현행과 같음)","no":"8"}]}