{"name":"경찰관 직무집행법","ef":"20251115","old":[{"content":"제5조(위험 발생의 방지 등) ① 경찰관은 사람의 생명 또는 신체에 위해를 끼치거나 재산에 중대한 손해를 끼칠 우려가 있는 천재(天災), 사변(事變), 인공구조물의 파손이나 붕괴, 교통사고, 위험물의 폭발, 위험한 동물 등의 출현, 극도의 혼잡, 그 밖의 위험한 사태가 있을 때에는 다음 각 호의 조치를 할 수 있다.","no":"1"},{"content":"1. (생  략)","no":"2"},{"content":"2. <P>매우 긴급</P>한 경우에는 위해를 입을 우려가 있는 사람을 필요한 한도에서 <P>억류하거나 피난시키</P>는 것","no":"3"},{"content":"<P>3. 그 장소에 있는 사람, 사물의 관리자, 그 밖의 관계인에게 위해를 방지하기 위하여 필요하다고 인정되는 조치를 하게 하거나 직접 그 조치를 하는 것</P>","no":"4"},{"content":"<P><신  설></P>","no":"5"},{"content":"② ∼ ④ (생  략)","no":"6"}],"new":[{"content":"제5조(위험 발생의 방지 등) ① 경찰관은 사람의 생명 또는 신체에 위해를 끼치거나 재산에 중대한 손해를 끼칠 우려가 있는 천재(天災), 사변(事變), 인공구조물의 파손이나 붕괴, 교통사고, 위험물의 폭발, 위험한 동물 등의 출현, 극도의 혼잡, 그 밖의 위험한 사태가 있을 때에는 다음 각 호의 조치를 할 수 있다.","no":"1"},{"content":"1. (현행과 같음)","no":"2"},{"content":"2. <P>긴급</P>한 경우에는 위해를 입을 우려가 있는 사람을 필요한 한도에서 <P>이동을 제한하거나 대피시키</P>는 것","no":"3"},{"content":"<P>3. 위험한 상황의 원인을 제공한 사람을 그 장소에서 퇴거시키거나 그 장소에의 접근을 금지시키는 것</P>","no":"4"},{"content":"<P>4. 그 장소에 있는 사람, 사물의 관리자, 그 밖의 관계인에게 위해를 방지하기 위하여 필요하다고 인정되는 조치를 하게 하거나 직접 그 조치를 하는 것</P>","no":"5"},{"content":"② ∼ ④ (현행과 같음)","no":"6"}]}