{"name":"동의대 사건 희생자의 명예회복 및 보상에 관한 법률","ef":"20260102","old":[{"content":"제3조(동의대 사건 희생자 명예회복 및 보상심의위원회) ① ∼ ③ (생  략)","no":"1"},{"content":"④ 제3항에 따른 관계 공무원에는 <P>기획재정부</P>, 법무부, 행정안전부, <P>국가보훈부</P>, 인사혁신처, 경찰청의 3급 이상 공무원 및 이에 상당하는 공무원으로서 소속 기관의 장이 추천하는 공무원이 포함되어야 한다.","no":"2"},{"content":"⑤ (생  략)","no":"3"}],"new":[{"content":"제3조(동의대 사건 희생자 명예회복 및 보상심의위원회) ① ∼ ③ (현행과 같음)","no":"1"},{"content":"④ 제3항에 따른 관계 공무원에는 <P>재정경제부</P>, 법무부, 행정안전부, <P>국가보훈부, 기획예산처</P>, 인사혁신처, 경찰청의 3급 이상 공무원 및 이에 상당하는 공무원으로서 소속 기관의 장이 추천하는 공무원이 포함되어야 한다.","no":"2"},{"content":"⑤ (현행과 같음)","no":"3"}]}