{"name":"병역법 시행령","ef":"20251001","old":[{"content":"제73조(병역지정업체의 선정 추천 등) ① 연구기관 또는 업체의 장(법인의 경우에는 그 대표자를 말한다. 이하 같다)은 법 제36조제1항에 따른 병역지정업체(연구기관의 경우에는 연구소 또는 연구분소, 공업 분야의 기간산업체 또는 방위산업체의 경우에는 공장 또는 사업장, 그 외의 분야는 업체를 말한다. 이하 같다)로 선정받으려는 경우에는 다음 각 호의 구분에 따른 추천을 받아야 한다.","no":"1"},{"content":"1. ∼ 4. (생  략)","no":"2"},{"content":"5. 「산업기술혁신 촉진법」 제19조에 따른 산업기술기반조성사업 실시 연구기관: <P>산업통상자원부장관</P>","no":"3"},{"content":"6. ∼ 8. (생  략)","no":"4"},{"content":"② ∼ ④ (생  략)","no":"5"}],"new":[{"content":"제73조(병역지정업체의 선정 추천 등) ① 연구기관 또는 업체의 장(법인의 경우에는 그 대표자를 말한다. 이하 같다)은 법 제36조제1항에 따른 병역지정업체(연구기관의 경우에는 연구소 또는 연구분소, 공업 분야의 기간산업체 또는 방위산업체의 경우에는 공장 또는 사업장, 그 외의 분야는 업체를 말한다. 이하 같다)로 선정받으려는 경우에는 다음 각 호의 구분에 따른 추천을 받아야 한다.","no":"1"},{"content":"1. ∼ 4. (현행과 같음)","no":"2"},{"content":"5. 「산업기술혁신 촉진법」 제19조에 따른 산업기술기반조성사업 실시 연구기관: <P>산업통상부장관</P>","no":"3"},{"content":"6. ∼ 8. (현행과 같음)","no":"4"},{"content":"② ∼ ④ (현행과 같음)","no":"5"}]}