{"name":"제주특별자치도 설치 및 국제자유도시 조성을 위한 특별법","ef":"20260301","old":[{"content":"제214조(초ㆍ중등교육에 관한 특례) ① 「초ㆍ중등교육법」 제4조제1항, 제13조제4항, 제14조제2항, 제18조의2제4항, 제18조의3제2항, 제27조제3항, 제30조제3항(교원 배치기준에 관한 사항은 제외한다), 제31조제3항, 제33조제2항, 제34조, 제34조의2제4항, 제43조제2항, 제47조제2항, 제60조제3항, 제60조의2제3항, <P>제60조의3제3항</P> 및 제63조제2항에서 대통령령 또는 교육부령으로 정하도록 한 사항은 도조례로 정할 수 있다.","no":"1"},{"content":"② (생  략)","no":"2"}],"new":[{"content":"제214조(초ㆍ중등교육에 관한 특례) ① 「초ㆍ중등교육법」 제4조제1항, 제13조제4항, 제14조제2항, 제18조의2제4항, 제18조의3제2항, 제27조제3항, 제30조제3항(교원 배치기준에 관한 사항은 제외한다), 제31조제3항, 제33조제2항, 제34조, 제34조의2제4항, 제43조제2항, 제47조제2항, 제60조제3항, 제60조의2제3항, <P>제60조의3제5항</P> 및 제63조제2항에서 대통령령 또는 교육부령으로 정하도록 한 사항은 도조례로 정할 수 있다.","no":"1"},{"content":"② (현행과 같음)","no":"2"}]}