{"name":"산업기술의 유출방지 및 보호에 관한 법률","ef":"20260603","old":[{"content":"제2조(정의) 이 법에서 사용하는 용어의 정의는 다음과 같다.","no":"1"},{"content":"1. “산업기술”이라 함은 제품 또는 용역의 개발ㆍ생산ㆍ보급 및 사용에 필요한 제반 방법 내지 기술상의 정보 중에서 행정기관의 장(해당 업무가 위임 또는 위탁된 경우에는 그 위임 또는 위탁받은 기관이나 법인ㆍ단체의 장을 말한다)이 산업경쟁력 제고나 유출방지 등을 위하여 이 법 또는 다른 법률이나 이 법 또는 다른 법률에서 위임한 명령(대통령령ㆍ총리령ㆍ부령에 한정한다. 이하 이 조에서 같다)에 따라 지정ㆍ고시ㆍ공고ㆍ인증하는 다음 각 목의 어느 하나에 해당하는 기술을 말한다.","no":"2"},{"content":"가.·나. (생  략)","no":"3"},{"content":"다. 「산업기술혁신 촉진법」 제15조의2에 따라 <P>인증</P>된 신기술","no":"4"},{"content":"라. ∼ 카. (생  략)","no":"5"},{"content":"2. ∼ 4. (생  략)","no":"6"}],"new":[{"content":"제2조(정의) 이 법에서 사용하는 용어의 정의는 다음과 같다.","no":"1"},{"content":"1. “산업기술”이라 함은 제품 또는 용역의 개발ㆍ생산ㆍ보급 및 사용에 필요한 제반 방법 내지 기술상의 정보 중에서 행정기관의 장(해당 업무가 위임 또는 위탁된 경우에는 그 위임 또는 위탁받은 기관이나 법인ㆍ단체의 장을 말한다)이 산업경쟁력 제고나 유출방지 등을 위하여 이 법 또는 다른 법률이나 이 법 또는 다른 법률에서 위임한 명령(대통령령ㆍ총리령ㆍ부령에 한정한다. 이하 이 조에서 같다)에 따라 지정ㆍ고시ㆍ공고ㆍ인증하는 다음 각 목의 어느 하나에 해당하는 기술을 말한다.","no":"2"},{"content":"가.·나. (현행과 같음)","no":"3"},{"content":"다. 「산업기술혁신 촉진법」 제15조의2에 따라 <P>지정</P>된 신기술","no":"4"},{"content":"라. ∼ 카. (현행과 같음)","no":"5"},{"content":"2. ∼ 4. (현행과 같음)","no":"6"}]}