{"name":"임업 및 산촌 진흥촉진에 관한 법률 시행령","ef":"20251223","old":[{"content":"제24조의3(산촌활성화지원센터의 지정 등) ① 법 제27조의3제1항제3호에서 “전문인력과 조직 등 대통령령으로 정하는 요건”이란 다음 각 호의 요건을 말한다.","no":"1"},{"content":"1. 임업인 교육, 산림자원을 활용한 창업 컨설팅 및 지원 업무를 수행한 경력이 있는 3명 이상의 전문인력으로 구성된 전담조직을 갖출 것 <P><후단 신설></P>","no":"2"},{"content":"2.·3. (생  략)","no":"3"},{"content":"② ∼ ⑥ (생  략)","no":"4"}],"new":[{"content":"제24조의3(산촌활성화지원센터의 지정 등) ① 법 제27조의3제1항제3호에서 “전문인력과 조직 등 대통령령으로 정하는 요건”이란 다음 각 호의 요건을 말한다.","no":"1"},{"content":"1. 임업인 교육, 산림자원을 활용한 창업 컨설팅 및 지원 업무를 수행한 경력이 있는 3명 이상의 전문인력으로 구성된 전담조직을 갖출 것. <P>이 경우 기관 또는 단체의 대표자가 임업인 교육, 산림자원을 활용한 창업 컨설팅 및 지원 업무를 수행한 경력이 있는 경우에는 그 대표자를 전문인력 산정에 포함한다.</P>","no":"2"},{"content":"2.·3. (현행과 같음)","no":"3"},{"content":"② ∼ ⑥ (현행과 같음)","no":"4"}]}