{"name":"행정업무의 운영 및 혁신에 관한 규정","ef":"20260102","old":[{"content":"제34조(특수 관인) ① (생  략)","no":"1"},{"content":"② 세입징수관, 지출관, 회계 등 재무에 관한 업무를 담당하는 공무원의 직인은 <P>기획재정부장관이</P>, 국립의 각급 학교에서 사용하는 관인은 교육부장관이, 외교부와 재외공관에서 외교문서에 사용하는 관인은 외교부장관이, 검찰기관에서 사용하는 관인은 법무부장관이, 군 기관에서 사용하는 관인은 국방부장관이 각각 그 규격과 등록 등 관리에 필요한 사항을 정한다.","no":"2"},{"content":"제55조(기관별 성과점검 등 관리) ①·② (생  략)","no":"3"},{"content":"③ 행정안전부장관은 제2항에 따른 종합점검 결과를 해당 중앙행정기관의 장, <P>기획재정부장관</P> 및 감사원장에게 통보해야 한다.","no":"4"},{"content":"④ <P>기획재정부장관</P>은 제3항에 따라 행정안전부장관으로부터 통보받은 점검결과를 다음 해 예산을 편성할 때에 반영할 수 있다.","no":"5"}],"new":[{"content":"제34조(특수 관인) ① (현행과 같음)","no":"1"},{"content":"② 세입징수관, 지출관, 회계 등 재무에 관한 업무를 담당하는 공무원의 직인은 <P>재정경제부장관 및 기획예산처장관이</P>, 국립의 각급 학교에서 사용하는 관인은 교육부장관이, 외교부와 재외공관에서 외교문서에 사용하는 관인은 외교부장관이, 검찰기관에서 사용하는 관인은 법무부장관이, 군 기관에서 사용하는 관인은 국방부장관이 각각 그 규격과 등록 등 관리에 필요한 사항을 정한다.","no":"2"},{"content":"제55조(기관별 성과점검 등 관리) ①·② (현행과 같음)","no":"3"},{"content":"③ 행정안전부장관은 제2항에 따른 종합점검 결과를 해당 중앙행정기관의 장, <P>기획예산처장관</P> 및 감사원장에게 통보해야 한다.","no":"4"},{"content":"④ <P>기획예산처장관</P>은 제3항에 따라 행정안전부장관으로부터 통보받은 점검결과를 다음 해 예산을 편성할 때에 반영할 수 있다.","no":"5"}]}