{"name":"소방청과 그 소속기관 직제 시행규칙","ef":"20260101","old":[{"content":"제3조(119대응국) ① ∼ ⑤ (생  략)","no":"1"},{"content":"⑥ 구급의료팀장은 다음 사항을 분장한다.","no":"2"},{"content":"1. ∼ 7. (생  략)","no":"3"},{"content":"<P><신  설></P>","no":"4"},{"content":"<P><신  설></P>","no":"5"},{"content":"제4조(화재예방국) ① 화재예방국에 <P>화재예방총괄과ㆍ소방분석제도과ㆍ위험물안전</P>과 및 생활안전과를 두며, <P>화재예방총괄과장은 소방준감으로, 소방분석제도과장ㆍ위험물안전과장</P> 및 생활안전과장은 과학기술서기관ㆍ서기관 또는 소방정으로 보한다.","no":"6"},{"content":"② <P>화재예방총괄과장</P>은 다음 사항을 분장한다.","no":"7"},{"content":"1. ∼ 13. (생  략)","no":"8"},{"content":"③ <P>소방분석제도과장</P>은 다음 사항을 분장한다.","no":"9"},{"content":"1. ∼ 17. (생  략)","no":"10"},{"content":"④·⑤ (생  략)","no":"11"},{"content":"제4조의2(장비기술국) ① 장비기술국에 <P>장비총괄과ㆍ소방항공과ㆍ정보통신과 및 소방산업과를 두며, 장비총괄과장</P>은 소방준감으로, 소방항공과장ㆍ정보통신과장 및 <P>소방산업과장</P>은 과학기술서기관ㆍ서기관 또는 소방정으로 보한다.","no":"12"},{"content":"② <P>장비총괄과장</P>은 다음 사항을 분장한다.","no":"13"},{"content":"1. ∼ 17. (생  략)","no":"14"},{"content":"③·④ (생  략)","no":"15"},{"content":"⑤ <P>소방산업과장</P>은 다음 사항을 분장한다.","no":"16"},{"content":"1. ∼ 16. (생  략)","no":"17"},{"content":"제8조의2(소방정대) ① 119특수구조대장 소속으로 <P>두는</P> 소방정대의 명칭ㆍ위치 및 관할구역은 별표 2의2와 같다.","no":"18"},{"content":"② <P>소방정대장</P>은 다음 사항을 분장한다.","no":"19"},{"content":"1. ∼ 6. (생  략)","no":"20"},{"content":"제9조(소방청에 두는 공무원의 정원) ① 소방청에 두는 공무원의 직급별 정원(「행정기관의 조직과 정원에 관한 통칙」 제25조제1항에 따른 한시정원은 제외한다. 이하 이 조에서 같다)은 별표 3과 같다. 다만, 「소방청과 그 소속기관 직제」 제22조제1항 단서에 따라 별표 3에 따른 총정원의 10퍼센트를 넘지 않는 범위에서 따로 정하는 공무원의 직급별 정원은 별표 3의2와 같으며, 별표 3의2의 정원 중 <P>1명(행정주사ㆍ공업주사ㆍ임업주사ㆍ간호주사ㆍ시설주사ㆍ방재안전주사ㆍ전산주사ㆍ방송통신주사ㆍ학예연구사ㆍ기록연구사ㆍ시설연구사</P> 또는 소방경 1명)은 임기제공무원으로 임용한다.","no":"21"},{"content":"② (생  략)","no":"22"},{"content":"③ 소방청에 두는 공무원 정원 중 공공데이터 관련 업무를 담당하는 <P>1명(5급</P> 1명)은 임기제공무원으로 임용한다.","no":"23"},{"content":"<P>제13조(국립소방병원건립추진단장) 국립소방병원건립추진단장 밑에 두는 공무원의 직급별 정원은 별표 7과 같다.</P>","no":"24"}],"new":[{"content":"제3조(119대응국) ① ∼ ⑤ (현행과 같음)","no":"1"},{"content":"⑥ 구급의료팀장은 다음 사항을 분장한다.","no":"2"},{"content":"1. ∼ 7. (현행과 같음)","no":"3"},{"content":"<P>8. 국립소방병원 운영ㆍ평가 및 지도ㆍ감독</P>","no":"4"},{"content":"<P>9. 국립소방병원 관련 법령의 입안 및 운영</P>","no":"5"},{"content":"제4조(화재예방국) ① 화재예방국에 <P>예방정책과ㆍ예방분석제도과ㆍ위험물안전</P>과 및 생활안전과를 두며, <P>예방정책과장은 소방준감으로, 예방분석제도과장ㆍ위험물안전과장</P> 및 생활안전과장은 과학기술서기관ㆍ서기관 또는 소방정으로 보한다.","no":"6"},{"content":"② <P>예방정책과장</P>은 다음 사항을 분장한다.","no":"7"},{"content":"1. ∼ 13. (현행과 같음)","no":"8"},{"content":"③ <P>예방분석제도과장</P>은 다음 사항을 분장한다.","no":"9"},{"content":"1. ∼ 17. (현행과 같음)","no":"10"},{"content":"④·⑤ (현행과 같음)","no":"11"},{"content":"제4조의2(장비기술국) ① 장비기술국에 <P>첨단장비과ㆍ소방항공과ㆍ정보통신과 및 소방산업진흥정책과를 두며, 첨단장비과장</P>은 소방준감으로, 소방항공과장ㆍ정보통신과장 및 <P>소방산업진흥정책과장</P>은 과학기술서기관ㆍ서기관 또는 소방정으로 보한다.","no":"12"},{"content":"② <P>첨단장비과장</P>은 다음 사항을 분장한다.","no":"13"},{"content":"1. ∼ 17. (현행과 같음)","no":"14"},{"content":"③·④ (현행과 같음)","no":"15"},{"content":"⑤ <P>소방산업진흥정책과장</P>은 다음 사항을 분장한다.","no":"16"},{"content":"1. ∼ 16. (현행과 같음)","no":"17"},{"content":"제8조의2(소방정대) ① 119특수구조대장 소속으로 <P>두는 각</P> 소방정대의 명칭ㆍ위치 및 관할구역은 별표 2의2와 같다.","no":"18"},{"content":"② <P>각 소방정대장</P>은 다음 사항을 분장한다.","no":"19"},{"content":"1. ∼ 6. (현행과 같음)","no":"20"},{"content":"제9조(소방청에 두는 공무원의 정원) ① 소방청에 두는 공무원의 직급별 정원(「행정기관의 조직과 정원에 관한 통칙」 제25조제1항에 따른 한시정원은 제외한다. 이하 이 조에서 같다)은 별표 3과 같다. 다만, 「소방청과 그 소속기관 직제」 제22조제1항 단서에 따라 별표 3에 따른 총정원의 10퍼센트를 넘지 않는 범위에서 따로 정하는 공무원의 직급별 정원은 별표 3의2와 같으며, 별표 3의2의 정원 중 <P>2명(행정사무관ㆍ공업사무관ㆍ의무사무관ㆍ간호사무관ㆍ시설사무관ㆍ방재안전사무관ㆍ전산사무관ㆍ방송통신사무관ㆍ기록연구관ㆍ공업연구관ㆍ시설연구관 또는 소방령 1명, 행정주사ㆍ공업주사ㆍ임업주사ㆍ간호주사ㆍ시설주사ㆍ방재안전주사ㆍ전산주사ㆍ방송통신주사ㆍ학예연구사ㆍ기록연구사ㆍ시설연구사</P> 또는 소방경 1명)은 임기제공무원으로 임용한다.","no":"21"},{"content":"② (현행과 같음)","no":"22"},{"content":"③ 소방청에 두는 공무원 정원 중 공공데이터 관련 업무를 담당하는 <P>1명(5급 1명) 및 디지털 홍보를 담당하는 1명(6급</P> 1명)은 임기제공무원으로 임용한다.","no":"23"},{"content":"<P><삭  제></P>","no":"24"}]}