{"name":"학점인정 등에 관한 법률 시행령","ef":"20260127","old":[{"content":"제7조의3(평가인정의 취소 및 시정명령 등) ① (생  략)","no":"1"},{"content":"② 법 <P>제5조제2항에 따른</P> 시정명령을 받은 자가 이를 이행하였을 때에는 지체 없이 교육부장관에게 <P>보고하여야</P> 한다.","no":"2"},{"content":"<P>③ 시정명령에 이의가 있는 자는 이를 통지받은 날부터 15일 이내에 관련 서류를 갖추어 교육부장관에게 이의신청을 할 수 있으며, 교육부장관은 특별한 사유가 없으면 30일 이내에 이를 심사한 후 그 결과를 신청인에게 통지하여야 한다.</P>","no":"3"}],"new":[{"content":"제7조의3(평가인정의 취소 및 시정명령 등) ① (현행과 같음)","no":"1"},{"content":"② 법 <P>제5조제2항 본문에 따른</P> 시정명령을 받은 자가 이를 이행하였을 때에는 지체 없이 교육부장관에게 <P>보고해야</P> 한다.","no":"2"},{"content":"<P>③ 법 제5조제2항 본문에 따른 시정명령에 이의가 있는 자의 이의신청에 관하여는 「행정기본법」 제36조에 따른다.</P>","no":"3"}]}