{"name":"학교보건법","ef":"20270301","old":[{"content":"제7조(건강검사 등) ① (생  략)","no":"1"},{"content":"② <P>학교의 장은 제1항에 따라</P> 건강검사를 할 때에 질병의 유무 등을 조사하거나 검사하기 위하여 다음 각 호의 어느 하나에 해당하는 학생에 대하여는 「국민건강보험법」 <P>제52조에 따른 건강검진 실시 기관에 의뢰하여 교육부령으로 정하는 사항에 대한 건강검사를 한다</P>.","no":"2"},{"content":"1. 「초ㆍ중등교육법」 제2조제1호의 학교와 이에 준하는 특수학교ㆍ각종학교의 1학년 및 4학년 학생. 다만, 구강검진은 전 학년에 대하여 <P>실시하되, 그 방법과 비용 등에 관한 사항은 지역실정에 따라 교육감이 정한다</P>.","no":"3"},{"content":"2.·3. (생  략)","no":"4"},{"content":"③ 학교의 장은 <P>제2항에 따른</P> 건강검사 외에 학생의 건강을 보호ㆍ증진하기 위하여 필요하다고 인정하면 교육부령으로 정하는 바에 따라 그 학생을 별도로 검사할 수 있다.","no":"5"},{"content":"④ 학교의 장은 <P>제1항과 제2항</P>에도 불구하고 천재지변 등 부득이한 사유로 관할 교육감 또는 교육장의 승인을 받은 경우에는 교육부령으로 정하는 바에 따라 건강검사를 연기하거나 건강검사의 전부 또는 일부를 생략할 수 있다.","no":"6"},{"content":"⑤ 제2항에 따라 건강검사를 <P>한 검진기관</P>은 교육부령으로 정하는 바에 따라 그 검사결과를 해당 학생 또는 학부모와 해당 학교의 장에게 알려야 한다.","no":"7"},{"content":"<P>⑥ 학교의 장은 제2조제1호의 정신건강 상태 검사를 실시할 때 필요한 경우에는 학부모의 동의 없이 실시할 수 있다. 이 경우 학교의 장은 지체 없이 해당 학부모에게 검사 사실을 통보하여야 한다.</P>","no":"8"},{"content":"<P>⑦ 제1항과 제2항에 따른 건강검사의 시기, 방법, 검사항목 및 절차 등에 관하여 필요한 사항은 교육부령으로 정한다.</P>","no":"9"},{"content":"<P><신  설></P>","no":"10"}],"new":[{"content":"제7조(건강검사 등) ① (현행과 같음)","no":"1"},{"content":"② <P>교육부장관은 제1항에도 불구하고</P> 건강검사를 할 때에 질병의 유무 등을 조사하거나 검사하기 위하여 다음 각 호의 어느 하나에 해당하는 학생에 대하여는 「국민건강보험법」 <P>제13조에 따른 국민건강보험공단(이하 이 조에서 “공단”이라 한다)에 위탁할 수 있다</P>.","no":"2"},{"content":"1. 「초ㆍ중등교육법」 제2조제1호의 학교와 이에 준하는 특수학교ㆍ각종학교의 1학년 및 4학년 학생. 다만, 구강검진은 전 학년에 대하여 <P>실시한다</P>.","no":"3"},{"content":"2.·3. (현행과 같음)","no":"4"},{"content":"③ 학교의 장은 <P>제1항에 따른</P> 건강검사 외에 학생의 건강을 보호ㆍ증진하기 위하여 필요하다고 인정하면 교육부령으로 정하는 바에 따라 그 학생을 별도로 검사할 수 있다.","no":"5"},{"content":"④ 학교의 장은 <P>제1항</P>에도 불구하고 천재지변 등 부득이한 사유로 관할 교육감 또는 교육장의 승인을 받은 경우에는 교육부령으로 정하는 바에 따라 건강검사를 연기하거나 건강검사의 전부 또는 일부를 생략할 수 있다.","no":"6"},{"content":"⑤ 제2항에 따라 건강검사를 <P>위탁받은 공단</P>은 교육부령으로 정하는 바에 따라 그 검사결과를 해당 학생 또는 학부모와 해당 학교의 장에게 알려야 한다.","no":"7"},{"content":"<P>⑥ 교육부장관은 제2항에 따라 건강검사를 공단에 위탁하는 경우 「초ㆍ중등교육법」 제30조의4에 따른 교육정보시스템과 「국민건강보험법」 제14조제1항제4호에 따른 건강정보시스템을 전자적으로 연계하여 활용할 수 있다. 이 경우 연계를 통하여 수집할 수 있는 자료 또는 정보는 제2항에 따라 공단에 위탁하는 건강검사에 관한 것으로 한정한다.</P>","no":"8"},{"content":"<P>⑦ 학교의 장은 제2조제1호의 정신건강 상태 검사를 실시할 때 필요한 경우에는 학부모의 동의 없이 실시할 수 있다. 이 경우 학교의 장은 지체 없이 해당 학부모에게 검사 사실을 통보하여야 한다.</P>","no":"9"},{"content":"<P>⑧ 제1항과 제2항에 따른 건강검사의 시기, 방법, 검사항목, 절차 및 위탁 등에 관하여 필요한 사항은 교육부령으로 정한다.</P>","no":"10"}]}