{"name":"대통령경호처와 그 소속기관 직제","ef":"20260219","old":[{"content":"제5조(하부조직) <P>① 대통령경호처에 기획관리실ㆍ경호본부ㆍ경비안전본부 및 지원본부를 둔다.</P>","no":"1"},{"content":"② <P>기획관리실장ㆍ경호본부장ㆍ경비안전본부장 및 지원본부장</P>은 2급 경호공무원으로 보한다.","no":"2"},{"content":"③·④ (생  략)","no":"3"},{"content":"⑤ <P>기획관리실</P>, 경호본부, 경비안전본부 및 <P>지원본부</P>의 하부조직 및 그 분장사무와 감사관의 분장사무는 처장이 정한다.","no":"4"}],"new":[{"content":"제5조(하부조직) <P>① 대통령경호처에 운영관리본부ㆍ경호본부ㆍ경비안전본부 및 첨단과학경호본부를 둔다.</P>","no":"1"},{"content":"② <P>운영관리본부장ㆍ경호본부장ㆍ경비안전본부장 및 첨단과학경호본부장</P>은 2급 경호공무원으로 보한다.","no":"2"},{"content":"③·④ (현행과 같음)","no":"3"},{"content":"⑤ <P>운영관리본부</P>, 경호본부, 경비안전본부 및 <P>첨단과학경호본부</P>의 하부조직 및 그 분장사무와 감사관의 분장사무는 처장이 정한다.","no":"4"}]}