{"name":"각종분쟁조정위원회등의조정조서등에대한집행문부여에관한규칙","ef":"20020701","old":[{"content":"제1조(목적) 이 규칙은 <P>민사소송법</P>이 적용 또는 준용되지 아니하는 법률의 규정에 의하여 재판상의 화해와 동일한 효력이 있는 문서에 대한 집행문의 부여절차 기타 필요한 사항을 규정함을 목적으로 한다.","no":"1"},{"content":"제8조(준용규정) 집행문의 부여절차와 비용의 예납등에 관하여는 이 규칙에 규정된 것을 제외하고는 <P>민사소송법 및 민사소송규칙</P>의 규정을 준용한다.","no":"2"}],"new":[{"content":"제1조(목적) 이 규칙은 <P>민사집행법</P>이 적용 또는 준용되지 아니하는 법률의 규정에 의하여 재판상의 화해와 동일한 효력이 있는 문서에 대한 집행문의 부여절차 기타 필요한 사항을 규정함을 목적으로 한다.","no":"1"},{"content":"제8조(준용규정) 집행문의 부여절차와 비용의 예납등에 관하여는 이 규칙에 규정된 것을 제외하고는 <P>민사집행법 및 민사집행규칙</P>의 규정을 준용한다.","no":"2"}]}